pentaquark/__init__.py
pentaquark/config.py
pentaquark/constants.py
pentaquark/db.py
pentaquark/exceptions.py
pentaquark/lookups.py
pentaquark/mixins.py
pentaquark/registry.py
pentaquark/settings.py
pentaquark/setup.py
pentaquark/contrib/__init__.py
pentaquark/contrib/state/__init__.py
pentaquark/contrib/state/models.py
pentaquark/graphql/__init__.py
pentaquark/graphql/mixins.py
pentaquark/graphql/refactoring.py
pentaquark/graphql/scalars.py
pentaquark/graphql/schema.py
pentaquark/graphql/typedefs.py
pentaquark/models/__init__.py
pentaquark/models/base.py
pentaquark/models/managers.py
pentaquark/models/nodes.py
pentaquark/patterns/__init__.py
pentaquark/properties/__init__.py
pentaquark/properties/choices.py
pentaquark/properties/composite.py
pentaquark/properties/computed_properties.py
pentaquark/properties/cypher_property.py
pentaquark/properties/files.py
pentaquark/properties/relationships.py
pentaquark/properties/scalars.py
pentaquark/properties/spatial.py
pentaquark/query_builders/__init__.py
pentaquark/query_builders/call_query_builder.py
pentaquark/query_builders/create_query_builder.py
pentaquark/query_builders/match_query_builder.py
pentaquark/query_builders/param_store.py
pentaquark/query_builders/pattern_builder.py
pentaquark/query_builders/predicates.py
pentaquark/query_builders/query_builder.py
pentaquark/query_builders/result_query_builder.py
pentaquark/query_builders/where_query_builder.py
pentaquark/registry/__init__.py
pentaquark/registry/decorators.py
pentaquark/registry/registry.py
pentaquark/relationships/__init__.py
pentaquark/relationships/enums.py
pentaquark/relationships/managers.py
pentaquark/relationships/models.py
pentaquark/utils/__init__.py
pentaquark/utils/decorators.py
pentaquark/utils/flatteners.py
pentaquark/utils/text.py
pentaquark-0.0.6.3.dist-info/LICENSE
pentaquark-0.0.6.3.dist-info/METADATA
pentaquark-0.0.6.3.dist-info/WHEEL
pentaquark-0.0.6.3.dist-info/top_level.txt
pentaquark-0.0.6.3.dist-info/RECORD
