Metadata-Version: 2.1
Name: pentaquark
Version: 0.0.6.3
Summary: UNKNOWN
Home-page: https://github.com/stellasia/pentaquark/
Author: Estelle Scifo
License: GPL-3.0
Keywords: neo4j,graphql
Platform: UNKNOWN
Requires-Python: >=3.9
Requires-Dist: neo4j
Requires-Dist: python-dotenv
Requires-Dist: python-slugify
Requires-Dist: ariadne
